odoo/addons/project_timesheet_time_control_sale/README.rst
odoo/addons/project_timesheet_time_control_sale/__init__.py
odoo/addons/project_timesheet_time_control_sale/__manifest__.py
odoo/addons/project_timesheet_time_control_sale/i18n/es.po
odoo/addons/project_timesheet_time_control_sale/i18n/it.po
odoo/addons/project_timesheet_time_control_sale/i18n/project_timesheet_time_control_sale.pot
odoo/addons/project_timesheet_time_control_sale/models/__init__.py
odoo/addons/project_timesheet_time_control_sale/models/account_analytic_line.py
odoo/addons/project_timesheet_time_control_sale/models/account_move_line.py
odoo/addons/project_timesheet_time_control_sale/readme/CONTRIBUTORS.rst
odoo/addons/project_timesheet_time_control_sale/readme/DESCRIPTION.rst
odoo/addons/project_timesheet_time_control_sale/static/description/icon.png
odoo/addons/project_timesheet_time_control_sale/static/description/icon.svg
odoo/addons/project_timesheet_time_control_sale/static/description/index.html
odoo/addons/project_timesheet_time_control_sale/wizards/__init__.py
odoo/addons/project_timesheet_time_control_sale/wizards/hr_timesheet_switch.py
odoo14_addon_project_timesheet_time_control_sale-14.0.1.0.1.dev11.dist-info/METADATA
odoo14_addon_project_timesheet_time_control_sale-14.0.1.0.1.dev11.dist-info/WHEEL
odoo14_addon_project_timesheet_time_control_sale-14.0.1.0.1.dev11.dist-info/top_level.txt
odoo14_addon_project_timesheet_time_control_sale-14.0.1.0.1.dev11.dist-info/RECORD
